sereena_parser/__init__.py
sereena_parser/main.py
sereena_parser-1.0.0.dist-info/licenses/LICENSE
sereena_parser-1.0.0.dist-info/METADATA
sereena_parser-1.0.0.dist-info/WHEEL
sereena_parser-1.0.0.dist-info/entry_points.txt
sereena_parser-1.0.0.dist-info/top_level.txt
sereena_parser-1.0.0.dist-info/RECORD
