Metadata-Version: 2.4
Name: sereena-parser
Version: 1.0.0
Summary: Production-ready resume parser with multi-threading support for PDF and DOCX files
Home-page: https://github.com/joelpawar08/sereena-parser
Author: Sereena Thomas
Author-email: Your Name <your.email@example.com>
License: MIT
Project-URL: Homepage, https://github.com/yourusername/sereena-parser
Project-URL: Repository, https://github.com/yourusername/sereena-parser
Project-URL: Bug Tracker, https://github.com/yourusername/sereena-parser/issues
Keywords: resume,parser,cv,pdf,docx,nlp,recruitment
Classifier: Development Status :: 4 - Beta
Classifier: Intended Audience :: Developers
Classifier: License :: OSI Approved :: MIT License
Classifier: Programming Language :: Python :: 3
Classifier: Programming Language :: Python :: 3.8
Classifier: Programming Language :: Python :: 3.9
Classifier: Programming Language :: Python :: 3.10
Classifier: Programming Language :: Python :: 3.11
Classifier: Programming Language :: Python :: 3.12
Classifier: Topic :: Text Processing :: Linguistic
Classifier: Topic :: Office/Business
Requires-Python: >=3.8
License-File: LICENSE
Requires-Dist: PyPDF2>=3.0.1
Requires-Dist: pdfplumber>=0.10.3
Requires-Dist: python-docx>=1.1.0
Requires-Dist: spacy>=3.7.2
Requires-Dist: pandas>=2.1.4
Requires-Dist: email-validator>=2.1.0
Requires-Dist: numpy>=1.25.2
Provides-Extra: dev
Requires-Dist: pytest>=7.4.3; extra == "dev"
Requires-Dist: pytest-cov>=4.1.0; extra == "dev"
Requires-Dist: black>=23.11.0; extra == "dev"
Requires-Dist: flake8>=6.1.0; extra == "dev"
Dynamic: author
Dynamic: home-page
Dynamic: license-file
Dynamic: requires-python
